qrpa/RateLimitedSender.py
qrpa/__init__.py
qrpa/db_migrator.py
qrpa/feishu_bot_app.py
qrpa/feishu_client.py
qrpa/feishu_logic.py
qrpa/fun_base.py
qrpa/fun_excel.py
qrpa/fun_file.py
qrpa/fun_web.py
qrpa/fun_win.py
qrpa/shein_daily_report_model.py
qrpa/shein_excel.py
qrpa/shein_lib.py
qrpa/shein_mysql.py
qrpa/shein_sqlite.py
qrpa/shein_ziniao.py
qrpa/temu_chrome.py
qrpa/temu_excel.py
qrpa/temu_lib.py
qrpa/time_utils.py
qrpa/time_utils_example.py
qrpa/wxwork.py
qrpa/mysql_module/__init__.py
qrpa/mysql_module/new_product_analysis_model.py
qrpa/mysql_module/shein_ledger_model.py
qrpa/mysql_module/shein_ledger_month_report_model.py
qrpa/mysql_module/shein_product_model.py
qrpa/mysql_module/shein_return_order_model.py
qrpa/mysql_module/shein_store_model.py
qrpa/mysql_module/shein_supplier_info_model.py
qrpa/mysql_module/shein_wallet_model.py
qrpa-1.1.84.dist-info/METADATA
qrpa-1.1.84.dist-info/WHEEL
qrpa-1.1.84.dist-info/top_level.txt
qrpa-1.1.84.dist-info/RECORD
