Metadata-Version: 2.4
Name: qrpa
Version: 1.1.84
Summary: qsir's rpa library
Author: QSir
Author-email: QSir <1171725650@qq.com>
License-Expression: GPL-3.0-or-later
Dynamic: author
